PoolTool/__init__.py
PoolTool/controller.py
PoolTool/layout.kv
PoolTool/model.py
PoolTool/scratch.py
PoolTool/view.py
PoolTool/assets/icon.jpg
PoolTool-2.1.2.dist-info/LICENSE
PoolTool-2.1.2.dist-info/METADATA
PoolTool-2.1.2.dist-info/WHEEL
PoolTool-2.1.2.dist-info/entry_points.txt
PoolTool-2.1.2.dist-info/top_level.txt
PoolTool-2.1.2.dist-info/RECORD
