Metadata-Version: 2.1
Name: PoolTool
Version: 2.1.2
Summary: A simple Python tool to help anyone use Liquidity Pools on the BitShares blockchain.
Home-page: https://github.com/iamredbar/PoolTool
Author: Brendan Jensen (iamredbar)
Author-email: iamredbar@protonmail.com
License: MIT
Platform: UNKNOWN
Classifier: License :: OSI Approved :: MIT License
Classifier: Programming Language :: Python :: 3.7
Classifier: Programming Language :: Python :: 3.8
Classifier: Programming Language :: Python :: 3.9
Requires-Dist: cython
Requires-Dist: bitshares
Requires-Dist: pypubsub
Requires-Dist: kivy
Requires-Dist: kivymd
